{
  "fun_score": 55,
  "fun_reason": "话题涉及价格波动和供应链问题，虽然与日常生活相关，但缺乏新颖性和娱乐性。车厘子涨价是常见的市场现象，传播性和趣味性有限。",
  "useful_score": 15,
  "useful_reason": "对消费者有一定实用价值，可以帮助用户了解价格趋势，做出购买决策。但解决的问题较为单一。",
  "total_score": 70,
  "has_idea": true,
  "product": {
    "name": "水果价格预警助手",
    "features": "实时监控进口水果价格波动，提供产地新闻、供应链分析和购买建议",
    "target_users": "喜欢购买进口水果的消费者、家庭主妇",
    "description": "通过整合产地新闻、气候数据和市场价格，帮助用户选择最佳购买时机"
  },
  "summary": "智利车厘子产区遭遇火灾，多个果园受损，预计产量下降15-20%，春节期间价格可能上涨30-50%，引发消费者担忧。",
  "analysis_notes": "虽然话题本身趣味性不高，但可以延伸为更广泛的水果价格监测工具，增加实用性和用户粘性。"
}
