{
  "fun_score": 62,
  "fun_reason": "这类'乌龙事件'具有天然的戏剧性和话题性，容易引发网友的好奇心和讨论欲。事件本身带有黑色幽默色彩，在社交媒体上有较强的传播性和娱乐性，网友可以进行调侃和二次创作。",
  "useful_score": 14,
  "useful_reason": "对企业内部沟通管理和系统安全有警示作用，可以提供风险防范和危机公关的案例参考。但对普通用户的直接实用价值有限，主要是娱乐和信息性质。",
  "total_score": 76,
  "has_idea": true,
  "product": {
    "name": "乌龙事件博物馆",
    "features": "收集整理各类企业乌龙事件、趣味性评分和排名、用户投票评选最搞笑乌龙、案例分析与防范建议、互动讨论社区",
    "target_users": "职场人士、企业管理者、爱好八卦的网友、公关从业者",
    "description": "记录和分享企业界各种啼笑皆非的乌龙事件，在娱乐中学习危机管理，在欢笑中警示风险。"
  },
  "summary": "2026年1月，携程系统误向全体员工发送离职通知引发恐慌，公司紧急解释为技术故障导致的测试信息误发，事件引发对企业内部沟通管理和系统安全的关注。",
  "analysis_notes": "这个话题具有很好的娱乐性和传播性，适合开发轻量级趣味产品。产品方向可以是乌龙事件合集、企业八卦社区、或危机管理学习平台。关键是在娱乐性和教育性之间找到平衡，既能吸引用户，又能提供价值。"
}
