{
  "fun_score": 62,
  "fun_reason": "折叠屏手机话题有一定科技感和新鲜度，'展开赢很大'的表述生动有趣。但主要是产品宣传性质，创意互动性一般。对科技爱好者有吸引力，但大众娱乐性中等。",
  "useful_score": 15,
  "useful_reason": "对考虑购买折叠屏手机的用户有参考价值，可以了解产品特性。但属于商业广告性质，实用性主要体现在购物决策辅助上，范围较窄。",
  "total_score": 77,
  "has_idea": true,
  "product": {
    "name": "折叠屏场景模拟器",
    "features": "AR模拟折叠屏展开效果、不同尺寸对比、应用场景演示、用户真实评价聚合",
    "target_users": "考虑购买折叠屏手机的潜在消费者、数码爱好者",
    "description": "让你在购买前真实体验折叠屏手机的大屏优势和使用场景"
  },
  "summary": "华为MateX7折叠屏旗舰发布，强调'展开赢很大'的大屏优势。内折叠设计提供平板级屏幕体验，在视频、文档、多任务等场景优势明显，体现折叠屏技术进步和市场认可",
  "analysis_notes": "产品话题有商业价值，可以做成购物决策工具。除了华为，可以扩展到所有折叠屏产品对比。AR体验功能如果能实现，会很有吸引力。"
}
