{
  "fun_score": 54,
  "fun_reason": "热播剧持续话题具有一定的娱乐性和社交传播价值。剧情讨论和角色分析能产生互动，经典台词和片段易于传播。但作为持续性话题，新鲜感和独特性相对有限。",
  "useful_score": 12,
  "useful_reason": "主要提供娱乐消遣和情感共鸣，实用价值较低。对追剧用户有一定的剧情参考价值，但难以解决实际问题或提供明显便利。",
  "total_score": 66,
  "has_idea": true,
  "product": {
    "name": "追剧热度分析器",
    "features": "实时追踪热播剧的热搜频次和讨论热度，分析剧情转折点和话题爆点，预测剧集走势，提供观众情绪趋势图",
    "target_users": "追剧爱好者、影视从业者、娱乐媒体编辑、剧集制作方",
    "description": "追踪热播剧话题热度和观众情绪，预测剧情走势和爆点时刻"
  },
  "summary": "电视剧《骄阳似我》持续热播，相关话题再登热搜。该剧以精彩表演、紧凑剧情和贴近现实的情感描写赢得观众喜爱，网友热烈讨论剧情和演技，展现优秀国产剧影响力。",
  "analysis_notes": "热播剧话题具有持续性和数据分析价值。可以开发热度追踪和趋势预测工具，服务追剧用户和影视从业者。总分66分，适合垂直领域产品。"
}
