{
  "fun_score": 64,
  "fun_reason": "高端品牌出现错误具有一定的戏剧性和讨论价值，容易引发关注。但事件本身较为严肃，娱乐性有限。收藏价值的讨论点增加了趣味性。",
  "useful_score": 10,
  "useful_reason": "对茅台消费者和收藏者有一定参考价值，可以了解产品质量问题和维权途径。但影响范围有限，实用性不高。",
  "total_score": 74,
  "has_idea": true,
  "product": {
    "name": "错版收藏品鉴定器",
    "features": "识别和鉴定各类错版产品（钞票、酒品、邮票等），评估收藏价值和真伪",
    "target_users": "收藏爱好者、高端消费品购买者",
    "description": "通过AI视觉识别错版产品特征，提供真伪鉴定和收藏价值评估"
  },
  "summary": "茅台马年生肖酒包装出现印刷错误，公司紧急道歉并启动召回，提供换货或退款。虽是印刷问题，但收藏家认为错版可能具有特殊价值。",
  "analysis_notes": "话题有一定吸引力，可以延伸为错版收藏品的鉴定和交易平台，满足收藏市场的细分需求。"
}
