{
  "fun_score": 68,
  "fun_reason": "亚洲杯作为重大体育赛事，具有强烈的娱乐性和传播性，能够引发球迷的激情和参与欲。比赛的不确定性和竞技对抗性带来观赏乐趣。但话题本身较为常规，缺乏特别的创意元素。",
  "useful_score": 16,
  "useful_reason": "对球迷来说有获取赛事信息、互动讨论的实用价值。可以提供赛程提醒、实时比分、球员数据等实用功能，帮助球迷更好地追踪比赛。",
  "total_score": 84,
  "has_idea": true,
  "product": {
    "name": "亚洲杯助手",
    "features": "实时比分推送、赛程提醒、球员数据分析、社区互动预测、精彩瞬间回放",
    "target_users": "亚洲杯球迷、足球爱好者、体育媒体从业者",
    "description": "一站式亚洲杯观赛伴侣，提供实时数据、智能提醒和球迷社区，让你不错过每一场精彩对决"
  },
  "summary": "2026年1月亚洲杯足球赛事引发热议，中国队表现备受关注，球迷热烈讨论战术和晋级前景，体现国内对亚洲足球的持续热情。",
  "analysis_notes": "体育赛事类热搜具有周期性和时效性，产品需要在赛事期间快速推出并抓住流量窗口期。可结合AI预测、数据可视化等技术增加产品吸引力。"
}
